ChatstatTikTokApi/__init__.py
ChatstatTikTokApi/exceptions.py
ChatstatTikTokApi/helpers.py
ChatstatTikTokApi/tiktok.py
ChatstatTikTokApi/utilities.py
ChatstatTikTokApi/api/__init__.py
ChatstatTikTokApi/api/comment.py
ChatstatTikTokApi/api/hashtag.py
ChatstatTikTokApi/api/search.py
ChatstatTikTokApi/api/sound.py
ChatstatTikTokApi/api/trending.py
ChatstatTikTokApi/api/user.py
ChatstatTikTokApi/api/video.py
ChatstatTikTokApi/browser_utilities/__init__.py
ChatstatTikTokApi/browser_utilities/browser.py
ChatstatTikTokApi/browser_utilities/browser_interface.py
ChatstatTikTokApi/browser_utilities/get_acrawler.py
examples/__init__.py
examples/comment_example.py
examples/hashtag_example.py
examples/search_example.py
examples/sound_example.py
examples/trending_example.py
examples/user_example.py
examples/video_example.py
tests/__init__.py
tests/test_comments.py
tests/test_hashtag.py
tests/test_integration.py
tests/test_search.py
tests/test_sound.py
tests/test_trending.py
tests/test_user.py
tests/test_video.py
ChatstatTikTokApi-5.3.2.dist-info/LICENSE
ChatstatTikTokApi-5.3.2.dist-info/LICENSE.txt
ChatstatTikTokApi-5.3.2.dist-info/METADATA
ChatstatTikTokApi-5.3.2.dist-info/WHEEL
ChatstatTikTokApi-5.3.2.dist-info/top_level.txt
ChatstatTikTokApi-5.3.2.dist-info/RECORD
