Metadata-Version: 2.1
Name: ChatstatTikTokApi
Version: 5.3.2
Summary: The Unofficial TikTok API Wrapper in Python 3 for our own Chatstat.
Home-page: https://github.com/j-teng96/TikTok-Api
Author: J Teng
Author-email: j.teng@chatstat.com
License: MIT
Download-URL: https://github.com/j-teng96/TikTok-Api/tree/master
Keywords: tiktok,python3,api,unofficial,tiktok-api,tiktok api
Platform: UNKNOWN
Classifier: Development Status :: 3 - Alpha
Classifier: Intended Audience :: Developers
Classifier: Topic :: Software Development :: Build Tools
Classifier: License :: OSI Approved :: MIT License
Classifier: Programming Language :: Python :: 3.7
Classifier: Programming Language :: Python :: 3.8
Classifier: Programming Language :: Python :: 3.9
Classifier: Programming Language :: Python :: 3.10
Requires-Dist: requests
Requires-Dist: playwright
